lephare/_lephare.cpython-310-darwin.so
lephare/runner.py
lephare/_version.py
lephare/filterSvc.py
lephare/__init__.py
lephare/_photoz.py
lephare/_spec.py
lephare/zphota.py
lephare/mag_gal.py
lephare/_pdf.py
lephare/filter.py
lephare/magSvc.py
lephare/_flt.py
lephare/sedtolib.py
lephare/_utils.py
lephare/.dylibs/libomp.dylib
lephare_dev-0.1.dist-info/RECORD
lephare_dev-0.1.dist-info/LICENSE
lephare_dev-0.1.dist-info/WHEEL
lephare_dev-0.1.dist-info/top_level.txt
lephare_dev-0.1.dist-info/METADATA
lib/flt.cpp
lib/PDF.cpp
lib/keyword.h
lib/onesource.h
lib/mag_gal.cpp
lib/filter_extinc.cpp
lib/oneElLambda.h
lib/opa.cpp
lib/flt.h
lib/Makefile
lib/cosmology.cpp
lib/_bindings.cc
lib/SED.h
lib/globals.h
lib/SED.cpp
lib/globals.cpp
lib/ext.cpp
lib/filter.cpp
lib/photoz_lib.h
lib/mag.cpp
lib/cosmology.h
lib/SEDLib.cpp
lib/sedtolib.cpp
lib/SEDLib.h
lib/mag.h
lib/ext_curv.cpp
lib/keyword.cpp
lib/photoz_lib.cpp
lib/zphota.cpp
lib/ext.h
lib/oneElLambda.cpp
lib/onesource.cpp
lib/opa.h
lib/PDF.h
