Metadata-Version: 2.1
Name: lephare-dev
Version: 0.1
Summary: LEPHARE photometric redshift estimator
Home-page: https://gitlab.lam.fr/Galaxies/LEPHARE
Author: Johann Cohen-Tanugi
Author-email: Johann Cohen-Tanugi <johann.cohentanugi@gmail.com>
License: MIT License
Project-URL: Source Code, https://github.com/lincc-frameworks/lephare
Classifier: Development Status :: 4 - Beta
Classifier: License :: OSI Approved :: MIT License
Classifier: Intended Audience :: Developers
Classifier: Intended Audience :: Science/Research
Classifier: Operating System :: OS Independent
Classifier: Programming Language :: Python
Requires-Python: >=3.9
License-File: LICENSE
Requires-Dist: matplotlib
Requires-Dist: numpy
Requires-Dist: astropy
Requires-Dist: scipy
Requires-Dist: requests
Provides-Extra: test
Requires-Dist: pytest; extra == "test"
Provides-Extra: dev
Requires-Dist: jupyter; extra == "dev"
Requires-Dist: pre-commit; extra == "dev"
Requires-Dist: pytest; extra == "dev"
Requires-Dist: pytest-cov; extra == "dev"
Requires-Dist: ruff; extra == "dev"
